{
  "submission_id": "mlp_sprint_922393_20250929_095830",
  "timestamp": "2025-09-29T09:58:30.727968",
  "team_name": "Speed Demons",
  "event_name": "mlp_sprint",
  "optimization_description": "Reduced hidden layer size for 2x speedup",
  "github_url": "https://github.com/speed-demons/fast-mlp",
  "performance_metrics": {
    "event": "MLP Sprint",
    "model_type": "FastMLPModel",
    "input_shape": [
      100,
      784
    ],
    "benchmark_timestamp": "2025-09-29T09:58:30.661651",
    "mean_inference_time": 0.0002917791799882252,
    "std_inference_time": 1.2687369326677067e-05,
    "min_inference_time": 0.0002747918000068239,
    "max_inference_time": 0.00031341669998710133,
    "p95_inference_time": 0.00030935165998926097,
    "mean_cpu_time": 0.0002917791799882252,
    "cpu_efficiency": 0.85,
    "profiling_method": "TinyTorch Module 15 Profiler",
    "memory_delta_mb": 0.004241943359375,
    "peak_memory_mb": 0.074676513671875,
    "result_size_mb": 0.1,
    "speedup_vs_baseline": 1.269967445986676
  },
  "speedup_score": 1.269967445986676,
  "baseline_time_ms": 0.3705500600017331,
  "submission_time_ms": 0.2917791799882252
}